openvino_openai_api/__init__.py
openvino_openai_api/app.py
openvino_openai_api/cli.py
openvino_openai_api/utils.py
openvino_openai_api-0.1.1.dist-info/LICENSE.md
openvino_openai_api-0.1.1.dist-info/METADATA
openvino_openai_api-0.1.1.dist-info/WHEEL
openvino_openai_api-0.1.1.dist-info/entry_points.txt
openvino_openai_api-0.1.1.dist-info/top_level.txt
openvino_openai_api-0.1.1.dist-info/RECORD
